music_pykg/__init__.py
music_pykg/check_nml.py
music_pykg/cli.py
music_pykg/constants.py
music_pykg/cpu_decomp.py
music_pykg/fgong.py
music_pykg/format1.py
music_pykg/format2.py
music_pykg/gravity.py
music_pykg/grid.py
music_pykg/ic_stellar.py
music_pykg/known_variables.py
music_pykg/namelist.py
music_pykg/pace_plot.py
music_pykg/parameters.json
music_pykg/particles.py
music_pykg/prof1d.py
music_pykg/py.typed
music_test/__init__.py
music_test/__main__.py
music_test/cli.py
music_test/cmake_builder.py
music_test/comparison_checks.py
music_test/coords.py
music_test/diffcalc.py
music_test/dirs.py
music_test/dumps.py
music_test/gravity.py
music_test/ic_gen.py
music_test/namelist.py
music_test/pipeline.py
music_test/py.typed
music_test/repo.py
music_test/runs.py
music_test/self_checks.py
music_test/source_tree.py
music_test/term.py
music_test/test.py
music_test/utils.py
music_test/validation.py
music_pykg-8.0.0.dist-info/METADATA
music_pykg-8.0.0.dist-info/WHEEL
music_pykg-8.0.0.dist-info/entry_points.txt
music_pykg-8.0.0.dist-info/RECORD
