Metadata-Version: 2.4
Name: music_pykg
Version: 8.0.0
Summary: Python tools to read MUSIC output files
Author-email: Thomas Guillet <t.a.guillet@exeter.ac.uk>, Adrien Morison <a.morison@exeter.ac.uk>
Requires-Python: >=3.10
Requires-Dist: f90nml>=1.4.4
Requires-Dist: h5py~=3.12
Requires-Dist: loam~=0.8.0
Requires-Dist: matplotlib>=3.9.2
Requires-Dist: music-mesa-tables~=0.2.2
Requires-Dist: numpy~=2.1
Requires-Dist: pandas~=2.2
Requires-Dist: rich>=13.9.4
Requires-Dist: scipy~=1.14
Requires-Dist: tomso>=0.2.1
